odoo/addons/product_brand_social_responsibility/README.rst
odoo/addons/product_brand_social_responsibility/__init__.py
odoo/addons/product_brand_social_responsibility/__manifest__.py
odoo/addons/product_brand_social_responsibility/i18n/product_brand_social_responsibility.pot
odoo/addons/product_brand_social_responsibility/models/__init__.py
odoo/addons/product_brand_social_responsibility/models/product_brand.py
odoo/addons/product_brand_social_responsibility/models/product_brand_tag_csr.py
odoo/addons/product_brand_social_responsibility/readme/CONTRIBUTORS.rst
odoo/addons/product_brand_social_responsibility/readme/DESCRIPTION.rst
odoo/addons/product_brand_social_responsibility/security/ir.model.access.csv
odoo/addons/product_brand_social_responsibility/security/ir_rule.xml
odoo/addons/product_brand_social_responsibility/static/description/icon.png
odoo/addons/product_brand_social_responsibility/static/description/index.html
odoo/addons/product_brand_social_responsibility/tests/__init__.py
odoo/addons/product_brand_social_responsibility/tests/test_product_brand.py
odoo/addons/product_brand_social_responsibility/views/product_brand_tag_csr_view.xml
odoo/addons/product_brand_social_responsibility/views/product_brand_view.xml
odoo14_addon_product_brand_social_responsibility-14.0.1.1.1.dist-info/METADATA
odoo14_addon_product_brand_social_responsibility-14.0.1.1.1.dist-info/WHEEL
odoo14_addon_product_brand_social_responsibility-14.0.1.1.1.dist-info/top_level.txt
odoo14_addon_product_brand_social_responsibility-14.0.1.1.1.dist-info/RECORD
